opendis/__init__.py
opendis/DataInputStream.py
opendis/DataOutputStream.py
opendis/dis7.py
opendis/PduFactory.py
opendis/RangeCoordinates.py
opendis/types.py
opendis-1.0.dist-info/LICENSE
opendis-1.0.dist-info/METADATA
opendis-1.0.dist-info/WHEEL
opendis-1.0.dist-info/RECORD
