Metadata-Version: 2.1
Name: opendis
Version: 1.0
Summary: implementation of DIS, IEEE-1278.1
Home-page: https://github.com/open-dis/open-dis-python
Author: Don McGregor
Author-email: mcgredo@nps.edu
Requires-Python: >=3.9,<4.0
Classifier: License :: OSI Approved :: BSD License
Classifier: Operating System :: OS Independent
Classifier: Programming Language :: Python :: 3
Classifier: Programming Language :: Python :: 3.9
Classifier: Programming Language :: Python :: 3.10
Classifier: Programming Language :: Python :: 3.11
Classifier: Programming Language :: Python :: 3.12
Classifier: Programming Language :: Python :: 3.13
Classifier: Topic :: Scientific/Engineering :: Interface Engine/Protocol Translator
Requires-Dist: numpy (>=1.26.4,<2.0.0)
Project-URL: Documentation, https://open-dis.org/
Project-URL: Repository, https://github.com/open-dis/open-dis-python
